{
  "projectId": "gen-lang-client-0121754260",
  "appId": "1:595174361340:web:5f3ac5e945c2c89f48af79",
  "apiKey": "AIzaSyA5nzUQdzNNJhSdgrfiM8hkD0FVu_n5KqU",
  "authDomain": "gen-lang-client-0121754260.firebaseapp.com",
  "firestoreDatabaseId": "ai-studio-victoryarenaespo-22a89eb0-4b83-4567-8432-43908d6700dc",
  "storageBucket": "gen-lang-client-0121754260.firebasestorage.app",
  "messagingSenderId": "595174361340",
  "measurementId": "",
  "oAuthClientId": "595174361340-mjuv121a99ot9efmiks0rb7k22j1uop4.apps.googleusercontent.com",
  "recaptchaSiteKey": ""
}